{"skeleton":{"hash":"zPeT6pBzti34BoMv6SHJWDutEfQ","spine":"3.5.51","width":737.17,"height":736.6,"images":"./images/"},"bones":[{"name":"root"},{"name":"Zhen","parent":"root","length":42.93,"rotation":74.57,"x":-4.42,"y":54.17,"color":"ffffffff"},{"name":"Guang","parent":"Zhen","x":20.81,"y":0.08,"color":"000000ff"},{"name":"Quan2","parent":"root","x":165.18,"y":70.15,"color":"ffe400ff"},{"name":"Quan","parent":"Quan2","length":33.65,"rotation":0.12,"x":0.08,"y":0.02,"color":"ff0202ff"},{"name":"Yingzi","parent":"root","x":87.22,"y":76.04,"color":"002dffff"}],"slots":[{"name":"Bg","bone":"root"},{"name":"Yingzi","bone":"Yingzi","attachment":"Yingzi"},{"name":"Quan2","bone":"Quan","attachment":"Quan"},{"name":"Quan","bone":"Quan","attachment":"Quan","blend":"additive"},{"name":"Guang","bone":"Guang","color":"ffffffcb","attachment":"Guang","blend":"additive"},{"name":"Zhen","bone":"Zhen","attachment":"Hongzhen"},{"name":"Zhen2","bone":"Zhen","color":"ffffff83","attachment":"Hongzhen","blend":"additive"}],"skins":{"default":{"Guang":{"Guang":{"x":2.45,"y":1.53,"rotation":-74.57,"width":40,"height":75}},"Quan":{"Quan":{"x":1.75,"y":0.46,"width":75,"height":74}},"Quan2":{"Quan":{"x":1.75,"y":0.46,"width":75,"height":74}},"Yingzi":{"Yingzi":{"x":-0.23,"y":0.13,"width":39,"height":22}},"Zhen":{"Fenzhen":{"x":23.47,"y":2.19,"rotation":-74.57,"width":29,"height":64},"Heizhen":{"x":25.4,"y":-4.25,"rotation":-74.57,"width":43,"height":64},"Hongzhen":{"x":25.57,"y":-4.35,"rotation":-74.57,"width":43,"height":64},"Huangzhen":{"x":25.28,"y":-4.36,"rotation":-74.57,"width":42,"height":64},"Lanzhen":{"x":25.98,"y":-4.23,"rotation":-74.57,"width":41,"height":64},"Lvzhen":{"x":25.36,"y":-4.11,"rotation":-74.57,"width":42,"height":63}},"Zhen2":{"Fenzhen":{"x":23.47,"y":2.19,"rotation":-74.57,"width":29,"height":64},"Heizhen":{"x":25.4,"y":-4.25,"rotation":-74.57,"width":43,"height":64},"Hongzhen":{"x":25.57,"y":-4.35,"rotation":-74.57,"width":43,"height":64},"Huangzhen":{"x":25.28,"y":-4.36,"rotation":-74.57,"width":42,"height":64},"Lanzhen":{"x":25.98,"y":-4.23,"rotation":-74.57,"width":41,"height":64},"Lvzhen":{"x":25.36,"y":-4.11,"rotation":-74.57,"width":42,"height":63}}}},"animations":{"Fen":{"slots":{"Guang":{"color":[{"time":0,"color":"eb5cffcb","curve":"stepped"},{"time":1.3333,"color":"eb5cffcb"}]},"Quan":{"color":[{"time":0,"color":"ffffff70"},{"time":0.3333,"color":"ffffff4c"},{"time":1,"color":"ffffff95"},{"time":1.3333,"color":"ffffff70"}]},"Quan2":{"color":[{"time":0,"color":"ffffffbe"},{"time":0.3333,"color":"ffffff7d"},{"time":1,"color":"ffffffff"},{"time":1.3333,"color":"ffffffbe"}]},"Zhen":{"attachment":[{"time":0,"name":"Fenzhen"},{"time":1.3333,"name":"Fenzhen"}]},"Zhen2":{"color":[{"time":0,"color":"ffffff86"},{"time":0.3333,"color":"ffffff52"},{"time":0.6667,"color":"ffffff86"},{"time":1,"color":"ffffffba"},{"time":1.3333,"color":"ffffff86"}],"attachment":[{"time":0,"name":"Fenzhen"},{"time":1.3333,"name":"Fenzhen"}]}},"bones":{"Quan":{"rotate":[{"time":0,"angle":0.58},{"time":0.3333,"angle":-87.93},{"time":0.6667,"angle":-179.25},{"time":1,"angle":89.76},{"time":1.3333,"angle":0.58}],"translate":[{"time":0,"x":0,"y":0,"curve":"stepped"},{"time":1.3333,"x":0,"y":0}],"scale":[{"time":0,"x":1,"y":1,"curve":"stepped"},{"time":1.3333,"x":1,"y":1}],"shear":[{"time":0,"x":0,"y":0,"curve":"stepped"},{"time":1.3333,"x":0,"y":0}]},"Quan2":{"rotate":[{"time":0,"angle":0,"curve":"stepped"},{"time":1.3333,"angle":0}],"translate":[{"time":0,"x":-165.86,"y":-61.45,"curve":"stepped"},{"time":1.3333,"x":-165.86,"y":-61.45}],"scale":[{"time":0,"x":1,"y":0.783,"curve":"stepped"},{"time":1.3333,"x":1,"y":0.783}],"shear":[{"time":0,"x":0,"y":0,"curve":"stepped"},{"time":1.3333,"x":0,"y":0}]},"Zhen":{"rotate":[{"time":0,"angle":0,"curve":"stepped"},{"time":1.3333,"angle":0}],"translate":[{"time":0,"x":1.86,"y":-25.12,"curve":[0.368,0.55,0.789,1]},{"time":0.3333,"x":1.86,"y":-22.96,"curve":[0.25,0,0.986,0.79]},{"time":1,"x":1.86,"y":-30.32,"curve":[0,0.26,0.462,0.67]},{"time":1.3333,"x":1.86,"y":-25.12}],"scale":[{"time":0,"x":1,"y":1,"curve":"stepped"},{"time":1.3333,"x":1,"y":1}],"shear":[{"time":0,"x":0,"y":0,"curve":"stepped"},{"time":1.3333,"x":0,"y":0}]},"Yingzi":{"rotate":[{"time":0,"angle":0,"curve":"stepped"},{"time":1.3333,"angle":0}],"translate":[{"time":0,"x":-87.78,"y":-67.45,"curve":"stepped"},{"time":1.3333,"x":-87.78,"y":-67.45}],"scale":[{"time":0,"x":0.956,"y":0.956,"curve":[0.368,0.54,0.789,1]},{"time":0.3333,"x":0.916,"y":0.916,"curve":[0.25,0,1,0.71]},{"time":1,"x":1.044,"y":1.044,"curve":[0,0.22,0.462,0.64]},{"time":1.3333,"x":0.956,"y":0.956}],"shear":[{"time":0,"x":0,"y":0,"curve":"stepped"},{"time":1.3333,"x":0,"y":0}]},"root":{"rotate":[{"time":0,"angle":0,"curve":"stepped"},{"time":1.3333,"angle":0}],"translate":[{"time":0,"x":0,"y":0,"curve":"stepped"},{"time":1.3333,"x":0,"y":0}],"scale":[{"time":0,"x":1,"y":1,"curve":"stepped"},{"time":1.3333,"x":1,"y":1}],"shear":[{"time":0,"x":0,"y":0,"curve":"stepped"},{"time":1.3333,"x":0,"y":0}]},"Guang":{"rotate":[{"time":0,"angle":0,"curve":"stepped"},{"time":1.3333,"angle":0}],"translate":[{"time":0,"x":0,"y":0,"curve":"stepped"},{"time":1.3333,"x":0,"y":0}],"scale":[{"time":0,"x":0.98,"y":0.98},{"time":0.3333,"x":0.96,"y":0.96},{"time":0.6667,"x":0.98,"y":0.98},{"time":1,"x":1,"y":1},{"time":1.3333,"x":0.98,"y":0.98}],"shear":[{"time":0,"x":0,"y":0,"curve":"stepped"},{"time":1.3333,"x":0,"y":0}]}}},"Hei":{"slots":{"Guang":{"color":[{"time":0,"color":"b58abccb","curve":"stepped"},{"time":1.3333,"color":"b58abccb"}]},"Quan":{"color":[{"time":0,"color":"ffffff70"},{"time":0.3333,"color":"ffffff4c"},{"time":1,"color":"ffffff95"},{"time":1.3333,"color":"ffffff70"}]},"Quan2":{"color":[{"time":0,"color":"ffffffbe"},{"time":0.3333,"color":"ffffff7d"},{"time":1,"color":"ffffffff"},{"time":1.3333,"color":"ffffffbe"}]},"Zhen":{"attachment":[{"time":0,"name":"Heizhen"},{"time":1.3333,"name":"Heizhen"}]},"Zhen2":{"color":[{"time":0,"color":"ffffff86"},{"time":0.3333,"color":"ffffff52"},{"time":0.6667,"color":"ffffff86"},{"time":1,"color":"ffffffba"},{"time":1.3333,"color":"ffffff86"}],"attachment":[{"time":0,"name":"Heizhen"},{"time":1.3333,"name":"Heizhen"}]}},"bones":{"Quan":{"rotate":[{"time":0,"angle":0.58},{"time":0.3333,"angle":-87.93},{"time":0.6667,"angle":-179.25},{"time":1,"angle":89.76},{"time":1.3333,"angle":0.58}],"translate":[{"time":0,"x":0,"y":0,"curve":"stepped"},{"time":1.3333,"x":0,"y":0}],"scale":[{"time":0,"x":1,"y":1,"curve":"stepped"},{"time":1.3333,"x":1,"y":1}],"shear":[{"time":0,"x":0,"y":0,"curve":"stepped"},{"time":1.3333,"x":0,"y":0}]},"Quan2":{"rotate":[{"time":0,"angle":0,"curve":"stepped"},{"time":1.3333,"angle":0}],"translate":[{"time":0,"x":-165.86,"y":-61.45,"curve":"stepped"},{"time":1.3333,"x":-165.86,"y":-61.45}],"scale":[{"time":0,"x":1,"y":0.783,"curve":"stepped"},{"time":1.3333,"x":1,"y":0.783}],"shear":[{"time":0,"x":0,"y":0,"curve":"stepped"},{"time":1.3333,"x":0,"y":0}]},"Zhen":{"rotate":[{"time":0,"angle":0,"curve":"stepped"},{"time":1.3333,"angle":0}],"translate":[{"time":0,"x":1.86,"y":-25.12,"curve":[0.368,0.55,0.789,1]},{"time":0.3333,"x":1.86,"y":-22.96,"curve":[0.25,0,0.986,0.79]},{"time":1,"x":1.86,"y":-30.32,"curve":[0,0.26,0.462,0.67]},{"time":1.3333,"x":1.86,"y":-25.12}],"scale":[{"time":0,"x":1,"y":1,"curve":"stepped"},{"time":1.3333,"x":1,"y":1}],"shear":[{"time":0,"x":0,"y":0,"curve":"stepped"},{"time":1.3333,"x":0,"y":0}]},"Yingzi":{"rotate":[{"time":0,"angle":0,"curve":"stepped"},{"time":1.3333,"angle":0}],"translate":[{"time":0,"x":-87.78,"y":-67.45,"curve":"stepped"},{"time":1.3333,"x":-87.78,"y":-67.45}],"scale":[{"time":0,"x":0.956,"y":0.956,"curve":[0.368,0.54,0.789,1]},{"time":0.3333,"x":0.916,"y":0.916,"curve":[0.25,0,1,0.71]},{"time":1,"x":1.044,"y":1.044,"curve":[0,0.22,0.462,0.64]},{"time":1.3333,"x":0.956,"y":0.956}],"shear":[{"time":0,"x":0,"y":0,"curve":"stepped"},{"time":1.3333,"x":0,"y":0}]},"root":{"rotate":[{"time":0,"angle":0,"curve":"stepped"},{"time":1.3333,"angle":0}],"translate":[{"time":0,"x":0,"y":0,"curve":"stepped"},{"time":1.3333,"x":0,"y":0}],"scale":[{"time":0,"x":1,"y":1,"curve":"stepped"},{"time":1.3333,"x":1,"y":1}],"shear":[{"time":0,"x":0,"y":0,"curve":"stepped"},{"time":1.3333,"x":0,"y":0}]},"Guang":{"rotate":[{"time":0,"angle":0,"curve":"stepped"},{"time":1.3333,"angle":0}],"translate":[{"time":0,"x":0,"y":0,"curve":"stepped"},{"time":1.3333,"x":0,"y":0}],"scale":[{"time":0,"x":0.98,"y":0.98},{"time":0.3333,"x":0.96,"y":0.96},{"time":0.6667,"x":0.98,"y":0.98},{"time":1,"x":1,"y":1},{"time":1.3333,"x":0.98,"y":0.98}],"shear":[{"time":0,"x":0,"y":0,"curve":"stepped"},{"time":1.3333,"x":0,"y":0}]}}},"Hong":{"slots":{"Guang":{"color":[{"time":0,"color":"ff0707cb","curve":"stepped"},{"time":1.3333,"color":"ff0707cb"}]},"Quan":{"color":[{"time":0,"color":"ffffff70"},{"time":0.3333,"color":"ffffff4c"},{"time":1,"color":"ffffff95"},{"time":1.3333,"color":"ffffff70"}]},"Quan2":{"color":[{"time":0,"color":"ffffffbe"},{"time":0.3333,"color":"ffffff7d"},{"time":1,"color":"ffffffff"},{"time":1.3333,"color":"ffffffbe"}]},"Zhen":{"attachment":[{"time":0,"name":"Hongzhen"},{"time":1.3333,"name":"Hongzhen"}]},"Zhen2":{"color":[{"time":0,"color":"ffffff86"},{"time":0.3333,"color":"ffffff52"},{"time":0.6667,"color":"ffffff86"},{"time":1,"color":"ffffffba"},{"time":1.3333,"color":"ffffff86"}],"attachment":[{"time":0,"name":"Hongzhen"},{"time":1.3333,"name":"Hongzhen"}]}},"bones":{"Quan":{"rotate":[{"time":0,"angle":0.58},{"time":0.3333,"angle":-87.93},{"time":0.6667,"angle":-179.25},{"time":1,"angle":89.76},{"time":1.3333,"angle":0.58}],"translate":[{"time":0,"x":0,"y":0,"curve":"stepped"},{"time":1.3333,"x":0,"y":0}],"scale":[{"time":0,"x":1,"y":1,"curve":"stepped"},{"time":1.3333,"x":1,"y":1}],"shear":[{"time":0,"x":0,"y":0,"curve":"stepped"},{"time":1.3333,"x":0,"y":0}]},"Quan2":{"rotate":[{"time":0,"angle":0,"curve":"stepped"},{"time":1.3333,"angle":0}],"translate":[{"time":0,"x":-165.86,"y":-61.45,"curve":"stepped"},{"time":1.3333,"x":-165.86,"y":-61.45}],"scale":[{"time":0,"x":1,"y":0.783,"curve":"stepped"},{"time":1.3333,"x":1,"y":0.783}],"shear":[{"time":0,"x":0,"y":0,"curve":"stepped"},{"time":1.3333,"x":0,"y":0}]},"Zhen":{"rotate":[{"time":0,"angle":0,"curve":"stepped"},{"time":1.3333,"angle":0}],"translate":[{"time":0,"x":1.86,"y":-25.12,"curve":[0.368,0.55,0.789,1]},{"time":0.3333,"x":1.86,"y":-22.96,"curve":[0.25,0,0.986,0.79]},{"time":1,"x":1.86,"y":-30.32,"curve":[0,0.26,0.462,0.67]},{"time":1.3333,"x":1.86,"y":-25.12}],"scale":[{"time":0,"x":1,"y":1,"curve":"stepped"},{"time":1.3333,"x":1,"y":1}],"shear":[{"time":0,"x":0,"y":0,"curve":"stepped"},{"time":1.3333,"x":0,"y":0}]},"Yingzi":{"rotate":[{"time":0,"angle":0,"curve":"stepped"},{"time":1.3333,"angle":0}],"translate":[{"time":0,"x":-87.78,"y":-67.45,"curve":"stepped"},{"time":1.3333,"x":-87.78,"y":-67.45}],"scale":[{"time":0,"x":0.956,"y":0.956,"curve":[0.368,0.54,0.789,1]},{"time":0.3333,"x":0.916,"y":0.916,"curve":[0.25,0,1,0.71]},{"time":1,"x":1.044,"y":1.044,"curve":[0,0.22,0.462,0.64]},{"time":1.3333,"x":0.956,"y":0.956}],"shear":[{"time":0,"x":0,"y":0,"curve":"stepped"},{"time":1.3333,"x":0,"y":0}]},"root":{"rotate":[{"time":0,"angle":0,"curve":"stepped"},{"time":1.3333,"angle":0}],"translate":[{"time":0,"x":0,"y":0,"curve":"stepped"},{"time":1.3333,"x":0,"y":0}],"scale":[{"time":0,"x":1,"y":1,"curve":"stepped"},{"time":1.3333,"x":1,"y":1}],"shear":[{"time":0,"x":0,"y":0,"curve":"stepped"},{"time":1.3333,"x":0,"y":0}]},"Guang":{"rotate":[{"time":0,"angle":0,"curve":"stepped"},{"time":1.3333,"angle":0}],"translate":[{"time":0,"x":0,"y":0,"curve":"stepped"},{"time":1.3333,"x":0,"y":0}],"scale":[{"time":0,"x":0.98,"y":0.98},{"time":0.3333,"x":0.96,"y":0.96},{"time":0.6667,"x":0.98,"y":0.98},{"time":1,"x":1,"y":1},{"time":1.3333,"x":0.98,"y":0.98}],"shear":[{"time":0,"x":0,"y":0,"curve":"stepped"},{"time":1.3333,"x":0,"y":0}]}}},"Huang":{"slots":{"Guang":{"color":[{"time":0,"color":"ffe400cb","curve":"stepped"},{"time":1.3333,"color":"ffe400cb"}]},"Quan":{"color":[{"time":0,"color":"ffffff70"},{"time":0.3333,"color":"ffffff4c"},{"time":1,"color":"ffffff95"},{"time":1.3333,"color":"ffffff70"}]},"Quan2":{"color":[{"time":0,"color":"ffffffbe"},{"time":0.3333,"color":"ffffff7d"},{"time":1,"color":"ffffffff"},{"time":1.3333,"color":"ffffffbe"}]},"Zhen":{"attachment":[{"time":0,"name":"Huangzhen"},{"time":1.3333,"name":"Huangzhen"}]},"Zhen2":{"color":[{"time":0,"color":"ffffff2d"},{"time":0.3333,"color":"ffffff18"},{"time":0.6667,"color":"ffffff2d"},{"time":1,"color":"ffffff43"},{"time":1.3333,"color":"ffffff2d"}],"attachment":[{"time":0,"name":"Huangzhen"},{"time":1.3333,"name":"Huangzhen"}]}},"bones":{"Quan":{"rotate":[{"time":0,"angle":0.58},{"time":0.3333,"angle":-87.93},{"time":0.6667,"angle":-179.25},{"time":1,"angle":89.76},{"time":1.3333,"angle":0.58}],"translate":[{"time":0,"x":0,"y":0,"curve":"stepped"},{"time":1.3333,"x":0,"y":0}],"scale":[{"time":0,"x":1,"y":1,"curve":"stepped"},{"time":1.3333,"x":1,"y":1}],"shear":[{"time":0,"x":0,"y":0,"curve":"stepped"},{"time":1.3333,"x":0,"y":0}]},"Quan2":{"rotate":[{"time":0,"angle":0,"curve":"stepped"},{"time":1.3333,"angle":0}],"translate":[{"time":0,"x":-165.86,"y":-61.45,"curve":"stepped"},{"time":1.3333,"x":-165.86,"y":-61.45}],"scale":[{"time":0,"x":1,"y":0.783,"curve":"stepped"},{"time":1.3333,"x":1,"y":0.783}],"shear":[{"time":0,"x":0,"y":0,"curve":"stepped"},{"time":1.3333,"x":0,"y":0}]},"Zhen":{"rotate":[{"time":0,"angle":0,"curve":"stepped"},{"time":1.3333,"angle":0}],"translate":[{"time":0,"x":1.86,"y":-25.12,"curve":[0.368,0.55,0.789,1]},{"time":0.3333,"x":1.86,"y":-22.96,"curve":[0.25,0,0.986,0.79]},{"time":1,"x":1.86,"y":-30.32,"curve":[0,0.26,0.462,0.67]},{"time":1.3333,"x":1.86,"y":-25.12}],"scale":[{"time":0,"x":1,"y":1,"curve":"stepped"},{"time":1.3333,"x":1,"y":1}],"shear":[{"time":0,"x":0,"y":0,"curve":"stepped"},{"time":1.3333,"x":0,"y":0}]},"Yingzi":{"rotate":[{"time":0,"angle":0,"curve":"stepped"},{"time":1.3333,"angle":0}],"translate":[{"time":0,"x":-87.78,"y":-67.45,"curve":"stepped"},{"time":1.3333,"x":-87.78,"y":-67.45}],"scale":[{"time":0,"x":0.956,"y":0.956,"curve":[0.368,0.54,0.789,1]},{"time":0.3333,"x":0.916,"y":0.916,"curve":[0.25,0,1,0.71]},{"time":1,"x":1.044,"y":1.044,"curve":[0,0.22,0.462,0.64]},{"time":1.3333,"x":0.956,"y":0.956}],"shear":[{"time":0,"x":0,"y":0,"curve":"stepped"},{"time":1.3333,"x":0,"y":0}]},"root":{"rotate":[{"time":0,"angle":0,"curve":"stepped"},{"time":1.3333,"angle":0}],"translate":[{"time":0,"x":0,"y":0,"curve":"stepped"},{"time":1.3333,"x":0,"y":0}],"scale":[{"time":0,"x":1,"y":1,"curve":"stepped"},{"time":1.3333,"x":1,"y":1}],"shear":[{"time":0,"x":0,"y":0,"curve":"stepped"},{"time":1.3333,"x":0,"y":0}]},"Guang":{"rotate":[{"time":0,"angle":0,"curve":"stepped"},{"time":1.3333,"angle":0}],"translate":[{"time":0,"x":0,"y":0,"curve":"stepped"},{"time":1.3333,"x":0,"y":0}],"scale":[{"time":0,"x":0.98,"y":0.98},{"time":0.3333,"x":0.96,"y":0.96},{"time":0.6667,"x":0.98,"y":0.98},{"time":1,"x":1,"y":1},{"time":1.3333,"x":0.98,"y":0.98}],"shear":[{"time":0,"x":0,"y":0,"curve":"stepped"},{"time":1.3333,"x":0,"y":0}]}}},"Lan":{"slots":{"Guang":{"color":[{"time":0,"color":"06d4ffcb","curve":"stepped"},{"time":1.3333,"color":"06d4ffcb"}]},"Quan":{"color":[{"time":0,"color":"ffffff70"},{"time":0.3333,"color":"ffffff4c"},{"time":1,"color":"ffffff95"},{"time":1.3333,"color":"ffffff70"}]},"Quan2":{"color":[{"time":0,"color":"ffffffbe"},{"time":0.3333,"color":"ffffff7d"},{"time":1,"color":"ffffffff"},{"time":1.3333,"color":"ffffffbe"}]},"Zhen":{"attachment":[{"time":0,"name":"Lanzhen"},{"time":1.3333,"name":"Lanzhen"}]},"Zhen2":{"color":[{"time":0,"color":"ffffff86"},{"time":0.3333,"color":"ffffff52"},{"time":0.6667,"color":"ffffff86"},{"time":1,"color":"ffffffba"},{"time":1.3333,"color":"ffffff86"}],"attachment":[{"time":0,"name":"Lanzhen"},{"time":1.3333,"name":"Lanzhen"}]}},"bones":{"Quan":{"rotate":[{"time":0,"angle":0.58},{"time":0.3333,"angle":-87.93},{"time":0.6667,"angle":-179.25},{"time":1,"angle":89.76},{"time":1.3333,"angle":0.58}],"translate":[{"time":0,"x":0,"y":0,"curve":"stepped"},{"time":1.3333,"x":0,"y":0}],"scale":[{"time":0,"x":1,"y":1,"curve":"stepped"},{"time":1.3333,"x":1,"y":1}],"shear":[{"time":0,"x":0,"y":0,"curve":"stepped"},{"time":1.3333,"x":0,"y":0}]},"Quan2":{"rotate":[{"time":0,"angle":0,"curve":"stepped"},{"time":1.3333,"angle":0}],"translate":[{"time":0,"x":-165.86,"y":-61.45,"curve":"stepped"},{"time":1.3333,"x":-165.86,"y":-61.45}],"scale":[{"time":0,"x":1,"y":0.783,"curve":"stepped"},{"time":1.3333,"x":1,"y":0.783}],"shear":[{"time":0,"x":0,"y":0,"curve":"stepped"},{"time":1.3333,"x":0,"y":0}]},"Zhen":{"rotate":[{"time":0,"angle":0,"curve":"stepped"},{"time":1.3333,"angle":0}],"translate":[{"time":0,"x":1.86,"y":-25.12,"curve":[0.368,0.55,0.789,1]},{"time":0.3333,"x":1.86,"y":-22.96,"curve":[0.25,0,0.986,0.79]},{"time":1,"x":1.86,"y":-30.32,"curve":[0,0.26,0.462,0.67]},{"time":1.3333,"x":1.86,"y":-25.12}],"scale":[{"time":0,"x":1,"y":1,"curve":"stepped"},{"time":1.3333,"x":1,"y":1}],"shear":[{"time":0,"x":0,"y":0,"curve":"stepped"},{"time":1.3333,"x":0,"y":0}]},"Yingzi":{"rotate":[{"time":0,"angle":0,"curve":"stepped"},{"time":1.3333,"angle":0}],"translate":[{"time":0,"x":-87.78,"y":-67.45,"curve":"stepped"},{"time":1.3333,"x":-87.78,"y":-67.45}],"scale":[{"time":0,"x":0.956,"y":0.956,"curve":[0.368,0.54,0.789,1]},{"time":0.3333,"x":0.916,"y":0.916,"curve":[0.25,0,1,0.71]},{"time":1,"x":1.044,"y":1.044,"curve":[0,0.22,0.462,0.64]},{"time":1.3333,"x":0.956,"y":0.956}],"shear":[{"time":0,"x":0,"y":0,"curve":"stepped"},{"time":1.3333,"x":0,"y":0}]},"root":{"rotate":[{"time":0,"angle":0,"curve":"stepped"},{"time":1.3333,"angle":0}],"translate":[{"time":0,"x":0,"y":0,"curve":"stepped"},{"time":1.3333,"x":0,"y":0}],"scale":[{"time":0,"x":1,"y":1,"curve":"stepped"},{"time":1.3333,"x":1,"y":1}],"shear":[{"time":0,"x":0,"y":0,"curve":"stepped"},{"time":1.3333,"x":0,"y":0}]},"Guang":{"rotate":[{"time":0,"angle":0,"curve":"stepped"},{"time":1.3333,"angle":0}],"translate":[{"time":0,"x":0,"y":0,"curve":"stepped"},{"time":1.3333,"x":0,"y":0}],"scale":[{"time":0,"x":0.98,"y":0.98},{"time":0.3333,"x":0.96,"y":0.96},{"time":0.6667,"x":0.98,"y":0.98},{"time":1,"x":1,"y":1},{"time":1.3333,"x":0.98,"y":0.98}],"shear":[{"time":0,"x":0,"y":0,"curve":"stepped"},{"time":1.3333,"x":0,"y":0}]}}},"Lv":{"slots":{"Guang":{"color":[{"time":0,"color":"05ff2acb","curve":"stepped"},{"time":1.3333,"color":"05ff2acb"}]},"Quan":{"color":[{"time":0,"color":"ffffff70"},{"time":0.3333,"color":"ffffff4c"},{"time":1,"color":"ffffff95"},{"time":1.3333,"color":"ffffff70"}]},"Quan2":{"color":[{"time":0,"color":"ffffffbe"},{"time":0.3333,"color":"ffffff7d"},{"time":1,"color":"ffffffff"},{"time":1.3333,"color":"ffffffbe"}]},"Zhen":{"attachment":[{"time":0,"name":"Lvzhen"},{"time":1.3333,"name":"Lvzhen"}]},"Zhen2":{"color":[{"time":0,"color":"ffffff86"},{"time":0.3333,"color":"ffffff52"},{"time":0.6667,"color":"ffffff86"},{"time":1,"color":"ffffffba"},{"time":1.3333,"color":"ffffff86"}],"attachment":[{"time":0,"name":"Lvzhen"},{"time":1.3333,"name":"Lvzhen"}]}},"bones":{"Quan":{"rotate":[{"time":0,"angle":0.58},{"time":0.3333,"angle":-87.93},{"time":0.6667,"angle":-179.25},{"time":1,"angle":89.76},{"time":1.3333,"angle":0.58}],"translate":[{"time":0,"x":0,"y":0,"curve":"stepped"},{"time":1.3333,"x":0,"y":0}],"scale":[{"time":0,"x":1,"y":1,"curve":"stepped"},{"time":1.3333,"x":1,"y":1}],"shear":[{"time":0,"x":0,"y":0,"curve":"stepped"},{"time":1.3333,"x":0,"y":0}]},"Quan2":{"rotate":[{"time":0,"angle":0,"curve":"stepped"},{"time":1.3333,"angle":0}],"translate":[{"time":0,"x":-165.86,"y":-61.45,"curve":"stepped"},{"time":1.3333,"x":-165.86,"y":-61.45}],"scale":[{"time":0,"x":1,"y":0.783,"curve":"stepped"},{"time":1.3333,"x":1,"y":0.783}],"shear":[{"time":0,"x":0,"y":0,"curve":"stepped"},{"time":1.3333,"x":0,"y":0}]},"Zhen":{"rotate":[{"time":0,"angle":0,"curve":"stepped"},{"time":1.3333,"angle":0}],"translate":[{"time":0,"x":1.86,"y":-25.12,"curve":[0.368,0.55,0.789,1]},{"time":0.3333,"x":1.86,"y":-22.96,"curve":[0.25,0,0.986,0.79]},{"time":1,"x":1.86,"y":-30.32,"curve":[0,0.26,0.462,0.67]},{"time":1.3333,"x":1.86,"y":-25.12}],"scale":[{"time":0,"x":1,"y":1,"curve":"stepped"},{"time":1.3333,"x":1,"y":1}],"shear":[{"time":0,"x":0,"y":0,"curve":"stepped"},{"time":1.3333,"x":0,"y":0}]},"Yingzi":{"rotate":[{"time":0,"angle":0,"curve":"stepped"},{"time":1.3333,"angle":0}],"translate":[{"time":0,"x":-87.78,"y":-67.45,"curve":"stepped"},{"time":1.3333,"x":-87.78,"y":-67.45}],"scale":[{"time":0,"x":0.956,"y":0.956,"curve":[0.368,0.54,0.789,1]},{"time":0.3333,"x":0.916,"y":0.916,"curve":[0.25,0,1,0.71]},{"time":1,"x":1.044,"y":1.044,"curve":[0,0.22,0.462,0.64]},{"time":1.3333,"x":0.956,"y":0.956}],"shear":[{"time":0,"x":0,"y":0,"curve":"stepped"},{"time":1.3333,"x":0,"y":0}]},"root":{"rotate":[{"time":0,"angle":0,"curve":"stepped"},{"time":1.3333,"angle":0}],"translate":[{"time":0,"x":0,"y":0,"curve":"stepped"},{"time":1.3333,"x":0,"y":0}],"scale":[{"time":0,"x":1,"y":1,"curve":"stepped"},{"time":1.3333,"x":1,"y":1}],"shear":[{"time":0,"x":0,"y":0,"curve":"stepped"},{"time":1.3333,"x":0,"y":0}]},"Guang":{"rotate":[{"time":0,"angle":0,"curve":"stepped"},{"time":1.3333,"angle":0}],"translate":[{"time":0,"x":0,"y":0,"curve":"stepped"},{"time":1.3333,"x":0,"y":0}],"scale":[{"time":0,"x":0.98,"y":0.98},{"time":0.3333,"x":0.96,"y":0.96},{"time":0.6667,"x":0.98,"y":0.98},{"time":1,"x":1,"y":1},{"time":1.3333,"x":0.98,"y":0.98}],"shear":[{"time":0,"x":0,"y":0,"curve":"stepped"},{"time":1.3333,"x":0,"y":0}]}}}}}